tokenizecpp.cpython-36m-darwin.so
tokenizecpp-1.0.0.dist-info/LICENSE
tokenizecpp-1.0.0.dist-info/METADATA
tokenizecpp-1.0.0.dist-info/WHEEL
tokenizecpp-1.0.0.dist-info/top_level.txt
tokenizecpp-1.0.0.dist-info/RECORD
