Metadata-Version: 2.1
Name: tokenizecpp
Version: 1.0.0
Summary: Tokenize C++ source code.
Home-page: UNKNOWN
Author: Ryusei Ishikawa
Author-email: UNKNOWN
License: MIT
Keywords: C++ tokenize
Platform: UNKNOWN
Requires-Dist: pybind11 (>=2.4)
